Takayasortfile/__init__.py
Takayasortfile/kanji_sort.py
Takayasortfile-1.0.1.dist-info/METADATA
Takayasortfile-1.0.1.dist-info/WHEEL
Takayasortfile-1.0.1.dist-info/top_level.txt
Takayasortfile-1.0.1.dist-info/RECORD
